data_algebra/BigQuery.py
data_algebra/MySQL.py
data_algebra/OrderedSet.py
data_algebra/PolarsSQL.py
data_algebra/PostgreSQL.py
data_algebra/SQLite.py
data_algebra/SparkSQL.py
data_algebra/__init__.py
data_algebra/arrow.py
data_algebra/cdata.py
data_algebra/connected_components.py
data_algebra/data_model.py
data_algebra/data_model_space.py
data_algebra/data_ops.py
data_algebra/data_ops_types.py
data_algebra/data_ops_utils.py
data_algebra/data_schema.py
data_algebra/data_space.py
data_algebra/db_model.py
data_algebra/db_space.py
data_algebra/eval_cache.py
data_algebra/expr_parse.py
data_algebra/expr_parse_fn.py
data_algebra/expr_rep.py
data_algebra/expression_walker.py
data_algebra/flow_text.py
data_algebra/fmt_python.py
data_algebra/near_sql.py
data_algebra/op_catalog.py
data_algebra/pandas_base.py
data_algebra/pandas_model.py
data_algebra/parse_by_lark.py
data_algebra/polars_model.py
data_algebra/python3_lark.py
data_algebra/shift_pipe_action.py
data_algebra/solutions.py
data_algebra/sql_format_options.py
data_algebra/sql_model.py
data_algebra/test_util.py
data_algebra/util.py
data_algebra/view_representations.py
data_algebra-1.7.1.dist-info/LICENSE
data_algebra-1.7.1.dist-info/METADATA
data_algebra-1.7.1.dist-info/WHEEL
data_algebra-1.7.1.dist-info/top_level.txt
data_algebra-1.7.1.dist-info/RECORD
