Metadata-Version: 2.1
Name: data-algebra
Version: 1.7.1
Summary: data_algebra is a data manipulation language that can both generate SQL queries and work on Pandas DataFrames.
Home-page: https://github.com/WinVector/data_algebra
Author: John Mount
Author-email: jmount@win-vector.com
License: License :: OSI Approved :: BSD 3-clause License
Platform: any
Classifier: Intended Audience :: Science/Research
Classifier: Programming Language :: Python
Classifier: Programming Language :: Python :: 3
Classifier: Programming Language :: Python :: 3.7
Classifier: Programming Language :: Python :: 3.8
Classifier: Programming Language :: Python :: 3.9
Classifier: Programming Language :: Python :: 3.10
Classifier: Programming Language :: Python :: 3.11
Classifier: License :: OSI Approved :: BSD License
Requires-Python: >=3.7
License-File: LICENSE
Requires-Dist: numpy >=1.25.0
Requires-Dist: pandas >=2.0.0
Requires-Dist: lark
Provides-Extra: bigquery
Requires-Dist: google.cloud ; extra == 'bigquery'
Requires-Dist: pyarrow ; extra == 'bigquery'
Requires-Dist: google-cloud-bigquery ; extra == 'bigquery'
Requires-Dist: db-dtypes ; extra == 'bigquery'
Provides-Extra: mysql
Requires-Dist: sqlalchemy ; extra == 'mysql'
Requires-Dist: pymysql ; extra == 'mysql'
Provides-Extra: polars
Requires-Dist: polars >=0.19.2 ; extra == 'polars'
Requires-Dist: pyarrow ; extra == 'polars'
Provides-Extra: postgresql
Requires-Dist: sqlalchemy ; extra == 'postgresql'
Requires-Dist: psycopg2 ; extra == 'postgresql'
Provides-Extra: spark
Requires-Dist: pyspark ; extra == 'spark'
Provides-Extra: all
Requires-Dist: black ; extra == 'all'
Requires-Dist: google.cloud ; extra == 'all'
Requires-Dist: pyarrow ; extra == 'all'
Requires-Dist: google-cloud-bigquery ; extra == 'all'
Requires-Dist: sqlalchemy ; extra == 'all'
Requires-Dist: psycopg2 ; extra == 'all'
Requires-Dist: pymysql ; extra == 'all'
Requires-Dist: pyspark ; extra == 'all'
Requires-Dist: polars >=0.15.3 ; extra == 'all'
Provides-Extra: pretty_python
Requires-Dist: black ; extra == 'pretty_python'
